onlinepybibtexer/format_bib_app.py
onlinepybibtexer-0.0.1.dist-info/METADATA
onlinepybibtexer-0.0.1.dist-info/WHEEL
onlinepybibtexer-0.0.1.dist-info/RECORD
