Metadata-Version: 2.4
Name: onlinepybibtexer
Version: 0.0.1
Summary: onlinepybibtexer
License: GPL-3.0-or-later
Keywords: Python,bibtex
Author: NextAI
Author-email: nextartifintell@gmail.com
Maintainer: NextAI
Maintainer-email: nextartifintell@gmail.com
Requires-Python: >=3.13
Classifier: License :: OSI Approved :: GNU General Public License v3 or later (GPLv3+)
Classifier: Programming Language :: Python :: 3
Classifier: Programming Language :: Python :: 3.13
Classifier: Programming Language :: Python :: 3.14
Classifier: Topic :: Software Development :: Libraries :: Python Modules
Requires-Dist: pyadvtools (>=0.0.5,<0.0.6)
Requires-Dist: pybibtexer (>=0.0.3,<0.0.4)
Requires-Dist: streamlit (>=1.49.1,<2.0.0)
Project-URL: Documentation, https://github.com/NextArtifIntell/onlinepybibtexer
Project-URL: Homepage, https://github.com/NextArtifIntell/onlinepybibtexer
Project-URL: Repository, https://github.com/NextArtifIntell/onlinepybibtexer
